{
    "plays": [],
    "settings_entries": {
        "ansible-navigator": {
            "ansible": {
                "config": {
                    "help": false
                },
                "doc": {
                    "help": false,
                    "plugin": {
                        "type": "module"
                    }
                },
                "inventory": {
                    "help": false
                },
                "playbook": {
                    "help": false,
                    "path": "/home/iva3682/.ansible/collections/ansible_collections/devops_81/hw_03/http.ansible.yml"
                }
            },
            "ansible-builder": {
                "help": false,
                "workdir": "/home/iva3682/.ansible/collections/ansible_collections/devops_81/hw_03"
            },
            "ansible-runner": {
                "job-events": false
            },
            "app": "run",
            "collection-doc-cache-path": "/home/iva3682/.cache/ansible-navigator/collection_doc_cache.db",
            "color": {
                "enable": true,
                "osc4": true
            },
            "editor": {
                "command": "vi +{line_number} {filename}",
                "console": true
            },
            "enable-prompts": false,
            "exec": {
                "command": "/bin/bash",
                "shell": true
            },
            "execution-environment": {
                "container-engine": "docker",
                "container-options": [
                    "--user=0"
                ],
                "enabled": true,
                "image": "hs_03_test:latest",
                "pull": {
                    "policy": "missing"
                }
            },
            "format": "yaml",
            "images": {
                "details": [
                    "everything"
                ]
            },
            "logging": {
                "append": true,
                "file": "/home/iva3682/.ansible/collections/ansible_collections/devops_81/hw_03/ansible-navigator.log",
                "level": "warning"
            },
            "mode": "stdout",
            "playbook-artifact": {
                "enable": true,
                "save-as": "{playbook_dir}/{playbook_name}-artifact-{time_stamp}.json"
            },
            "settings": {
                "effective": false,
                "sample": false,
                "schema": "json",
                "sources": false
            },
            "time-zone": "UTC"
        }
    },
    "settings_sources": {
        "ansible-navigator.ansible-builder.help": "Defaults",
        "ansible-navigator.ansible-builder.workdir": "Defaults",
        "ansible-navigator.ansible-lint.config": "Not set",
        "ansible-navigator.ansible-lint.lintables": "Not set",
        "ansible-navigator.ansible-runner.artifact-dir": "Not set",
        "ansible-navigator.ansible-runner.job-events": "Defaults",
        "ansible-navigator.ansible-runner.rotate-artifacts-count": "Not set",
        "ansible-navigator.ansible-runner.timeout": "Not set",
        "ansible-navigator.ansible.cmdline": "Not set",
        "ansible-navigator.ansible.config.help": "Defaults",
        "ansible-navigator.ansible.config.path": "Not set",
        "ansible-navigator.ansible.doc.help": "Defaults",
        "ansible-navigator.ansible.doc.plugin.name": "Not set",
        "ansible-navigator.ansible.doc.plugin.type": "Defaults",
        "ansible-navigator.ansible.inventory.entries": "Not set",
        "ansible-navigator.ansible.inventory.help": "Defaults",
        "ansible-navigator.ansible.playbook.help": "Defaults",
        "ansible-navigator.ansible.playbook.path": "Command line",
        "ansible-navigator.app": "Command line",
        "ansible-navigator.collection-doc-cache-path": "Defaults",
        "ansible-navigator.color.enable": "Defaults",
        "ansible-navigator.color.osc4": "Defaults",
        "ansible-navigator.editor.command": "Defaults",
        "ansible-navigator.editor.console": "Defaults",
        "ansible-navigator.enable-prompts": "Defaults",
        "ansible-navigator.exec.command": "Defaults",
        "ansible-navigator.exec.shell": "Defaults",
        "ansible-navigator.execution-environment.container-engine": "Automatically determined",
        "ansible-navigator.execution-environment.container-options": "Command line",
        "ansible-navigator.execution-environment.enabled": "Defaults",
        "ansible-navigator.execution-environment.environment-variables.pass": "Not set",
        "ansible-navigator.execution-environment.environment-variables.set": "Not set",
        "ansible-navigator.execution-environment.image": "Command line",
        "ansible-navigator.execution-environment.pull.arguments": "Not set",
        "ansible-navigator.execution-environment.pull.policy": "Command line",
        "ansible-navigator.execution-environment.volume-mounts": "Not set",
        "ansible-navigator.format": "Defaults",
        "ansible-navigator.images.details": "Defaults",
        "ansible-navigator.inventory-columns": "Not set",
        "ansible-navigator.logging.append": "Defaults",
        "ansible-navigator.logging.file": "Defaults",
        "ansible-navigator.logging.level": "Defaults",
        "ansible-navigator.mode": "Command line",
        "ansible-navigator.playbook-artifact.enable": "Defaults",
        "ansible-navigator.playbook-artifact.replay": "Not set",
        "ansible-navigator.playbook-artifact.save-as": "Defaults",
        "ansible-navigator.settings.effective": "Defaults",
        "ansible-navigator.settings.sample": "Defaults",
        "ansible-navigator.settings.schema": "Defaults",
        "ansible-navigator.settings.sources": "Defaults",
        "ansible-navigator.time-zone": "Defaults",
        "settings_file_path": "None",
        "settings_file_source": "None"
    },
    "status": "failed",
    "status_color": 9,
    "stdout": [
        "\u001b[1;35m[WARNING]: No inventory was parsed, only implicit localhost is available\u001b[0m",
        "\u001b[1;35m[WARNING]: provided hosts list is empty, only localhost is available. Note that\u001b[0m",
        "\u001b[1;35mthe implicit localhost does not match 'all'\u001b[0m",
        "",
        "PLAY [Create Nginx] ************************************************************",
        "",
        "TASK [Gathering Facts] *********************************************************",
        "\u001b[0;32mok: [localhost]\u001b[0m",
        "",
        "TASK [http : Update apt cache] *************************************************",
        "\u001b[1;35m[WARNING]: Updating cache and auto-installing missing dependency: python3-apt\u001b[0m",
        "\u001b[0;31mfatal: [localhost]: FAILED! => {\"changed\": false, \"cmd\": \"update\", \"msg\": \"[Errno 2] No such file or directory: b'update'\", \"rc\": 2, \"stderr\": \"\", \"stderr_lines\": [], \"stdout\": \"\", \"stdout_lines\": []}\u001b[0m",
        "",
        "PLAY RECAP *********************************************************************",
        "\u001b[0;31mlocalhost\u001b[0m                  : \u001b[0;32mok=1   \u001b[0m changed=0    unreachable=0    \u001b[0;31mfailed=1   \u001b[0m skipped=0    rescued=0    ignored=0   "
    ],
    "version": "2.0.0"
}
